odoo8_addon_l10n_fr_base_location_geonames_import-8.0.0.1.0.99.dev7-py2.7-nspkg.pth
odoo8_addon_l10n_fr_base_location_geonames_import-8.0.0.1.0.99.dev7.dist-info/METADATA
odoo8_addon_l10n_fr_base_location_geonames_import-8.0.0.1.0.99.dev7.dist-info/RECORD
odoo8_addon_l10n_fr_base_location_geonames_import-8.0.0.1.0.99.dev7.dist-info/WHEEL
odoo8_addon_l10n_fr_base_location_geonames_import-8.0.0.1.0.99.dev7.dist-info/namespace_packages.txt
odoo8_addon_l10n_fr_base_location_geonames_import-8.0.0.1.0.99.dev7.dist-info/top_level.txt
odoo_addons/l10n_fr_base_location_geonames_import/__init__.py
odoo_addons/l10n_fr_base_location_geonames_import/__openerp__.py
odoo_addons/l10n_fr_base_location_geonames_import/i18n/fr.po
odoo_addons/l10n_fr_base_location_geonames_import/i18n/it.po
odoo_addons/l10n_fr_base_location_geonames_import/i18n/l10n_fr_base_location_geonames_import.pot
odoo_addons/l10n_fr_base_location_geonames_import/i18n/sl.po
odoo_addons/l10n_fr_base_location_geonames_import/i18n/tr.po
odoo_addons/l10n_fr_base_location_geonames_import/static/description/icon.png
odoo_addons/l10n_fr_base_location_geonames_import/wizard/__init__.py
odoo_addons/l10n_fr_base_location_geonames_import/wizard/geonames_import.py
