Metadata-Version: 2.1
Name: odoo8-addon-l10n-fr-base-location-geonames-import
Version: 8.0.0.1.0.99.dev7
Summary: France-specific tuning for import of better zip entries from Geonames
Home-page: http://www.akretion.com
Author: Akretion,Odoo Community Association (OCA)
Author-email: support@odoo-community.org
License: AGPL-3
Platform: UNKNOWN
Classifier: Programming Language :: Python
Classifier: Framework :: Odoo
Classifier: License :: OSI Approved :: GNU Affero General Public License v3
Requires-Python: ~=2.7
Requires-Dist: odoo8-addon-base-location-geonames-import
Requires-Dist: odoo (<9.0a,>=8.0a)
Requires-Dist: unidecode
